setup.py
pySW4/__init__.py
pySW4.egg-info/PKG-INFO
pySW4.egg-info/SOURCES.txt
pySW4.egg-info/dependency_links.txt
pySW4.egg-info/entry_points.txt
pySW4.egg-info/pbr.json
pySW4.egg-info/requires.txt
pySW4.egg-info/top_level.txt
pySW4/core/__init__.py
pySW4/core/config.py
pySW4/core/header.py
pySW4/core/image.py
pySW4/core/scripts/__init__.py
pySW4/core/scripts/create_all_plots.py
pySW4/core/scripts/png2mp4.py
pySW4/plotting/__init__.py
pySW4/plotting/drape.py
pySW4/plotting/image.py
pySW4/plotting/util.py
pySW4/plotting/waveforms.py
pySW4/preprocess/__init__.py
pySW4/preprocess/grid_seismograms.py
pySW4/preprocess/material_model.py
pySW4/preprocess/rfileIO.py
pySW4/preprocess/source.py
pySW4/preprocess/stations.py
pySW4/utils/__init__.py
pySW4/utils/fourier_spectrum.py
pySW4/utils/geo.py
pySW4/utils/psde.py
pySW4/utils/utils.py