Metadata-Version: 1.1
Name: pySW4
Version: 0.2.2
Summary: Python routines for interaction with SW4
Home-page: https://github.com/shaharkadmiel/pySW4
Author: Shahar Shani-Kadmiel, Omry Volk, Tobias Megies
Author-email: kadmiel@post.bgu.ac.il
License: UNKNOWN
Download-URL: https://github.com/shaharkadmiel/pySW4.git
Keywords: pySW4,seismology,SW4
Platform: UNKNOWN
Classifier: Programming Language :: Python
Classifier: Development Status :: 4 - Beta
Classifier: Intended Audience :: Science/Research
Classifier: Intended Audience :: Developers
Classifier: License :: OSI Approved :: GNU General Public License v3 (GPLv3)
Classifier: Operating System :: OS Independent
Classifier: Topic :: Software Development :: Libraries :: Python Modules
